{
  "_metadata": {
    "version": "1.1",
    "description": "Controle do projeto ativo para isolamento de contexto",
    "last_updated": "2025-06-18T00:00:00Z"
  },
  "active_project": "personal-mcp-project",
  "activated_at": "2025-06-18T00:00:00Z",
  "session_id": "sess_personal_mcp_jun18_init",
  "last_command": "criar projeto personal-mcp-project",
  "last_command_at": "2025-06-18T23:00:00Z",
  "commands_count": 1,
  "session_duration": "documentação",
  "discovery_status": "PERSONAL MCP PROJECT CRIADO",
  "project_type": "sistema-revolucionario",
  "project_path": "rules/context/projects/personal-mcp-project/",
  "notes": "CRIADO: Personal MCP Project em 18 de junho de 2025. Sistema MCP exclusivo para revolucionar Zoe com IA 10x mais inteligente, performance <100ms e personalização máxima."
} 